{"docs": [{"url": "http://jcsites.juniata.edu/faculty/rhodes/os/ch8a.htm", "content_type": "Summary of key-concept(s)"}, {"url": "https://stackoverflow.com/a/14070788", "content_type": "Summary of key-concept(s)"}, {"url": "https://en.wikipedia.org/wiki/Virtual_memory", "content_type": "Explains key-concept(s)"}, {"url": "http://web.stanford.edu/~ouster/cgi-bin/cs140-spring14/index.php", "content_type": "Schedule for the lesson plan"}, {"url": "https://en.wikipedia.org/wiki/Memory_management_(operating_systems)", "content_type": "Explains key-concept(s)"}, {"url": "https://cs.nyu.edu/~gottlieb/courses/2000s/2004-05-fall/os/lectures/lecture-08.html", "content_type": "Explains key-concept(s)"}, {"url": "https://en.wikipedia.org/wiki/C_dynamic_memory_allocation", "content_type": "Explains key-concept(s)"}, {"url": "https://www.cs.uic.edu/~jbell/CourseNotes/OperatingSystems/9_VirtualMemory.html", "content_type": "Explains key-concept(s)"}, {"url": "https://gabrieletolomei.wordpress.com/miscellanea/operating-systems/virtual-memory-paging-and-swapping/", "content_type": "Explains key-concept(s)"}, {"url": "http://faculty.salina.k-state.edu/tim/ossg/index.html", "content_type": "Schedule for the lesson plan"}]}